esmf_regrid/__init__.py
esmf_regrid/_esmf_sdo.py
esmf_regrid/constants.py
esmf_regrid/esmf_regridder.py
esmf_regrid/schemes.py
esmf_regrid/experimental/__init__.py
esmf_regrid/experimental/io.py
esmf_regrid/experimental/unstructured_regrid.py
esmf_regrid/experimental/unstructured_scheme.py
esmf_regrid/tests/__init__.py
esmf_regrid/tests/conftest.py
esmf_regrid/tests/integration/__init__.py
esmf_regrid/tests/integration/esmf_regridder/__init__.py
esmf_regrid/tests/integration/esmf_regridder/test_Regridder.py
esmf_regrid/tests/integration/experimental/__init__.py
esmf_regrid/tests/integration/experimental/unstructured_scheme/__init__.py
esmf_regrid/tests/integration/experimental/unstructured_scheme/test_regrid_unstructured_to_rectilinear.py
esmf_regrid/tests/results/unit/_esmf_sdo/test_GridInfo/small_grid.txt
esmf_regrid/tests/results/unit/experimental/unstructured_regrid/test_MeshInfo/small_mesh.txt
esmf_regrid/tests/unit/__init__.py
esmf_regrid/tests/unit/_esmf_sdo/__init__.py
esmf_regrid/tests/unit/_esmf_sdo/test_GridInfo.py
esmf_regrid/tests/unit/_esmf_sdo/test_RefinedGridInfo.py
esmf_regrid/tests/unit/esmf_regridder/__init__.py
esmf_regrid/tests/unit/esmf_regridder/test_Constants.py
esmf_regrid/tests/unit/esmf_regridder/test_Regridder.py
esmf_regrid/tests/unit/experimental/__init__.py
esmf_regrid/tests/unit/experimental/io/__init__.py
esmf_regrid/tests/unit/experimental/io/test_load_regridder.py
esmf_regrid/tests/unit/experimental/io/test_round_tripping.py
esmf_regrid/tests/unit/experimental/io/test_save_regridder.py
esmf_regrid/tests/unit/experimental/io/v0.9_regridder.nc
esmf_regrid/tests/unit/experimental/unstructured_regrid/__init__.py
esmf_regrid/tests/unit/experimental/unstructured_regrid/test_MeshInfo.py
esmf_regrid/tests/unit/experimental/unstructured_scheme/__init__.py
esmf_regrid/tests/unit/experimental/unstructured_scheme/test_GridToMeshESMFRegridder.py
esmf_regrid/tests/unit/experimental/unstructured_scheme/test_MeshToGridESMFRegridder.py
esmf_regrid-0.13.1.dist-info/licenses/LICENSE
esmf_regrid-0.13.1.dist-info/METADATA
esmf_regrid-0.13.1.dist-info/WHEEL
esmf_regrid-0.13.1.dist-info/top_level.txt
esmf_regrid-0.13.1.dist-info/RECORD
