Metadata-Version: 2.4
Name: esmf_regrid
Version: 0.13.1
Summary: Iris regridding scheme using ESMF
Author-email: ESMF Regrid Contributors <scitools.pub@gmail.com>
License-Expression: BSD-3-Clause
Project-URL: Code, https://github.com/SciTools/iris-esmf-regrid
Project-URL: Docs, https://iris-esmf-regrid.readthedocs.io/en/stable
Project-URL: Issues, https://github.com/SciTools/iris-esmf-regrid/issues
Keywords: esmf,regrid
Classifier: Development Status :: 4 - Beta
Classifier: Intended Audience :: Science/Research
Classifier: Natural Language :: English
Classifier: Operating System :: OS Independent
Classifier: Programming Language :: Python :: 3
Classifier: Programming Language :: Python :: 3.11
Classifier: Programming Language :: Python :: 3.12
Classifier: Programming Language :: Python :: 3.13
Classifier: Topic :: Scientific/Engineering :: Atmospheric Science
Requires-Python: >=3.11
License-File: LICENSE
Requires-Dist: cartopy>=0.18
Requires-Dist: cf-units
Requires-Dist: numpy>=1.14
Requires-Dist: scipy
Requires-Dist: scitools-iris
Provides-Extra: dev
Requires-Dist: asv; extra == "dev"
Requires-Dist: codecov; extra == "dev"
Requires-Dist: nox; extra == "dev"
Requires-Dist: pre-commit; extra == "dev"
Requires-Dist: pytest; extra == "dev"
Requires-Dist: pytest-cov; extra == "dev"
Provides-Extra: docs
Requires-Dist: pydata-sphinx-theme; extra == "docs"
Requires-Dist: sphinx; extra == "docs"
Requires-Dist: sphinx-copybutton; extra == "docs"
Requires-Dist: sphinxcontrib-apidoc; extra == "docs"
Dynamic: license-file
